pyolap/__init__.py
pyolap/communication.py
pyolap/euclidolap.py
pyolap/mdmodels.py
pyolap/utils.py
tests/__init__.py
tests/test_01.py
tests/test_02.py
tests/test_03.py
tests/test_04_build_cube.py
tests/test_05_insert_measures.py
tests/test_06_query_0.py
tests/test_06_query_1.py
tests/test_99_auto_inserting_measures.py
pyolap-0.1.6.dist-info/METADATA
pyolap-0.1.6.dist-info/WHEEL
pyolap-0.1.6.dist-info/top_level.txt
pyolap-0.1.6.dist-info/RECORD
